trucksim/__init__.py
trucksim/can_env.py
trucksim/config.py
trucksim/utils.py
trucksim/cli/__init__.py
trucksim/cli/candump.py
trucksim/cli/cangen.py
trucksim/cli/cansend.py
trucksim/ecus/__init__.py
trucksim/ecus/body_controller_ecu.py
trucksim/ecus/brake_ecu.py
trucksim/ecus/engine_ecu.py
trucksim/ecus/transmission_ecu.py
trucksim-0.1.0.dist-info/LICENSE
trucksim-0.1.0.dist-info/METADATA
trucksim-0.1.0.dist-info/WHEEL
trucksim-0.1.0.dist-info/entry_points.txt
trucksim-0.1.0.dist-info/top_level.txt
trucksim-0.1.0.dist-info/RECORD
