Metadata-Version: 2.1
Name: trucksim
Version: 0.1.0
Summary: Virtual CAN simulation package for educational use
Home-page: https://github.com/yourusername/trucksim
Author: Your Name
Author-email: your.email@example.com
Classifier: Programming Language :: Python :: 3
Classifier: License :: OSI Approved :: MIT License
Classifier: Operating System :: OS Independent
Requires-Python: >=3.7
License-File: LICENSE
Requires-Dist: python-can
